tf_big-0.2.1.data/purelib/tf_big/__init__.py
tf_big-0.2.1.data/purelib/tf_big/python/__init__.py
tf_big-0.2.1.data/purelib/tf_big/python/tensor.py
tf_big-0.2.1.data/purelib/tf_big/python/ops/__init__.py
tf_big-0.2.1.data/purelib/tf_big/python/ops/_big_ops.so
tf_big-0.2.1.data/purelib/tf_big/python/ops/big_ops.py
tf_big-0.2.1.data/purelib/tf_big/python/test/__init__.py
tf_big-0.2.1.data/purelib/tf_big/python/test/execution_context.py
tf_big-0.2.1.dist-info/METADATA
tf_big-0.2.1.dist-info/WHEEL
tf_big-0.2.1.dist-info/top_level.txt
tf_big-0.2.1.dist-info/RECORD
