Metadata-Version: 2.1
Name: tf-big
Version: 0.2.1
Summary: Arbitrary precision integers in TensorFlow.
Home-page: https://github.com/tf-encrypted/tf-big
Author: The TF Encrypted Authors
Author-email: contact@tf-encrypted.io
License: Apache License 2.0
Platform: UNKNOWN
Classifier: Programming Language :: Python :: 3
Classifier: License :: OSI Approved :: Apache Software License
Classifier: Development Status :: 2 - Pre-Alpha
Classifier: Operating System :: OS Independent
Classifier: Topic :: Scientific/Engineering :: Artificial Intelligence
Classifier: Topic :: Security :: Cryptography
Requires-Python: >=3.5
Requires-Dist: pip (>=20.1.1)
Requires-Dist: numpy (>=1.14)
Provides-Extra: nightly
Requires-Dist: tf-nightly ; extra == 'nightly'
Provides-Extra: tf
Requires-Dist: tensorflow (~=2.2.0) ; extra == 'tf'
